{"PlayerInventory":{"itemStacks":[{"itemType":"Fire","count":100},{"itemType":"Air","count":75},{"itemType":"Water","count":74},{"itemType":"Grass","count":4},{"itemType":"Sapling","count":1},{"itemType":"Soil","count":27},{"itemType":"Plantation","count":4}]},"Buildings":[{"gathererType":"FireJar","outputInventory":{"itemStacks":[{"itemType":"Fire","count":14}]},"gridPosition":{"x":-1,"y":0},"direction":0},{"machineType":"LightSource","inputInventory":{"itemStacks":[]},"outputInventory":{"itemStacks":[]},"gridPosition":{"x":1,"y":0},"direction":0},{"gathererType":"AirJar","outputInventory":{"itemStacks":[{"itemType":"Air","count":13}]},"gridPosition":{"x":-1,"y":1},"direction":0},{"gathererType":"WaterJar","outputInventory":{"itemStacks":[{"itemType":"Water","count":14}]},"gridPosition":{"x":-1,"y":2},"direction":0},{"gathererType":"EarthJar","outputInventory":{"itemStacks":[{"itemType":"Soil","count":14}]},"gridPosition":{"x":-1,"y":3},"direction":0},{"machineType":"Plantation","inputInventory":{"itemStacks":[]},"outputInventory":{"itemStacks":[]},"gridPosition":{"x":1,"y":3},"direction":0}],"UnlockedStages":["0 Root","1 Light Source","2 Light","3 Water And Air","4 Soil and Farming","5 Campfire"]}